[{"device":"A","behavior":"BUILD_UP","object_type":"","object":"","time":"2015-03-26 19:57:38","done":"DBnul","statusid":"93"},{"device":"A","behavior":"BUILD_UP","object_type":"","object":"","time":"2015-03-26 19:59:18","done":"Dnull","statusid":"94"},{"device":"A","behavior":"BUILD_UP","object_type":"","object":"","time":"2015-03-26 19:59:52","done":"Dnull","statusid":"95"},{"device":"A","behavior":"BUILD_UP","object_type":"","object":"","time":"2015-03-26 20:15:45","done":"Dnull","statusid":"96"},{"device":"A","behavior":"BUILD_UP","object_type":"","object":"","time":"2015-03-26 20:17:14","done":"Dnull","statusid":"97"},{"device":"A","behavior":"BUILD_UP","object_type":"","object":"","time":"2015-03-26 20:21:28","done":"Dnull","statusid":"98"}]
